Workbook
Name Aporte: 'Projeto Dio'!$D$17:$D$17
Name Patrimonio: 'Projeto Dio'!$D$20:$D$20
Name Quantidade_anos: 'Projeto Dio'!$D$18:$D$18
Name Rendimento_Carteira: 'Projeto Dio'!$D$13:$D$13
Name Taxa_R_Mensal: 'Projeto Dio'!$D$19:$D$19
Name Valor_Investido: 'Projeto Dio'!$D$17:$D$17

Sheet Projeto Dio
B11: Configurações
B12: Salário | D12: 5000
B13: Rendimento Carteira | D13: 0.006
B14: Sugestão de Investimento | D14: =D12*30% -> 1500
B16: INVESTIMENTO MENSAL
B17: Valor Investido ao mês | D17: 500
B18: Quantidade de anos | D18: 5
B19: Taxa de Rendimento Mensal | D19: 0.01079
B20: Patrimônio Acumulado | D20: {=FV(Taxa_R_Mensal,Quantidade_anos*12,Valor_Investido*-1)} -> 41888.457
B21: Dividendos Mensais | D21: {=Patrimonio*Rendimento_Carteira} -> 251.33074
B23: Cenários | D23: Dividendos
A24: 2 | B24: Valor em 2 anos | C24: {=FV(Taxa_R_Mensal,A$24*12,Valor_Investido*-1)} -> 13613.814 | D24: {=C24*Rendimento_Carteira} -> 81.682882
A25: 5 | B25: Valor em 5 anos | C25: =FV($D$19,$A$25*12,$D$17*-1) -> 41888.457 | D25: {=C25*Rendimento_Carteira} -> 251.33074
A26: 10 | B26: Valor em 10 anos | C26: =FV($D$19,$A$26*12,$D$17*-1) -> 121642.11 | D26: {=C26*Rendimento_Carteira} -> 729.85264
A27: 20 | B27: Valor em 20 anos | C27: =FV($D$19,$A$27*12,$D$17*-1) -> 562599.2 | D27: {=C27*Rendimento_Carteira} -> 3375.5952
A28: 30 | B28: Valor em 30 anos | C28: =FV($D$19,$A$28*12,$D$17*-1) -> 2161084.8 | D28: {=C28*Rendimento_Carteira} -> 12966.509
B32: Perfil | C32: Agressivo
B33: Valor Investido Mensalmente | C33: {=Aporte} -> 500
B35: TIPO DE FII | C35: % SUGERIDO | D35: VALORES
B36: PAPEL | C36: =VLOOKUP($C$32&"-"&B36,Apoio!A2:D20,4,FALSE) -> 0.5 | D36: =$C$33*C36 -> 250
B37: TIJOLO | C37: =VLOOKUP($C$32&"-"&B37,Apoio!A3:D21,4,FALSE) -> 0.1 | D37: =$C$33*C37 -> 50
B38: HIBRIDOS | C38: =VLOOKUP($C$32&"-"&B38,Apoio!A4:D22,4,FALSE) -> 0.05 | D38: =$C$33*C38 -> 25
B39: FOFs | C39: =VLOOKUP($C$32&"-"&B39,Apoio!A5:D23,4,FALSE) -> 0.05 | D39: =$C$33*C39 -> 25
B40: DESENVOLVIMENTO | C40: =VLOOKUP($C$32&"-"&B40,Apoio!A6:D24,4,FALSE) -> 0.2 | D40: =$C$33*C40 -> 100
B41: HOTELARIAS | C41: =VLOOKUP($C$32&"-"&B41,Apoio!A7:D25,4,FALSE) -> 0.1 | D41: =$C$33*C41 -> 50
D42: =SUM(D36:D41) -> 500

Sheet Apoio
A2: CHAVE COMPOSTA | B2: PERFIL | C2: TIPO DE FII | D2: %
A3: =$B$3&"-"&C3 -> Conservador-PAPEL | B3: Conservador | C3: PAPEL | D3: 0.3
A4: =$B$3&"-"&C4 -> Conservador-TIJOLO | B4: Conservador | C4: TIJOLO | D4: 0.5
A5: =$B$3&"-"&C5 -> Conservador-HIBRIDOS | B5: Conservador | C5: HIBRIDOS | D5: 0.1
A6: =$B$3&"-"&C6 -> Conservador-FOFs | B6: Conservador | C6: FOFs | D6: 0.1
A7: =$B$3&"-"&C7 -> Conservador-DESENVOLVIMENTO | B7: Conservador | C7: DESENVOLVIMENTO | D7: 0
A8: =$B$3&"-"&C8 -> Conservador-HOTELARIAS | B8: Conservador | C8: HOTELARIAS | D8: 0
A9: =$B$9&"-"&C9 -> Moderado-PAPEL | B9: Moderado | C9: PAPEL | D9: 0.32
A10: =$B$9&"-"&C10 -> Moderado-TIJOLO | B10: Moderado | C10: TIJOLO | D10: 0.35
A11: =$B$9&"-"&C11 -> Moderado-HIBRIDOS | B11: Moderado | C11: HIBRIDOS | D11: 0.08
A12: =$B$9&"-"&C12 -> Moderado-FOFs | B12: Moderado | C12: FOFs | D12: 0.05
A13: =$B$9&"-"&C13 -> Moderado-DESENVOLVIMENTO | B13: Moderado | C13: DESENVOLVIMENTO | D13: 0.1
A14: =$B$9&"-"&C14 -> Moderado-HOTELARIAS | B14: Moderado | C14: HOTELARIAS | D14: 0.1
A15: =$B$15&"-"&C15 -> Agressivo-PAPEL | B15: Agressivo | C15: PAPEL | D15: 0.5
A16: =$B$15&"-"&C16 -> Agressivo-TIJOLO | B16: Agressivo | C16: TIJOLO | D16: 0.1
A17: =$B$15&"-"&C17 -> Agressivo-HIBRIDOS | B17: Agressivo | C17: HIBRIDOS | D17: 0.05
A18: =$B$15&"-"&C18 -> Agressivo-FOFs | B18: Agressivo | C18: FOFs | D18: 0.05
A19: =$B$15&"-"&C19 -> Agressivo-DESENVOLVIMENTO | B19: Agressivo | C19: DESENVOLVIMENTO | D19: 0.2
A20: =$B$15&"-"&C20 -> Agressivo-HOTELARIAS | B20: Agressivo | C20: HOTELARIAS | D20: 0.1
